qsharp_preview-0.0.12.dist-info/METADATA
qsharp_preview-0.0.12.dist-info/WHEEL
qsharp/.data/qsharp_codemirror.js
qsharp/_ipython.py
qsharp/_native.pyi
qsharp/_qsharp.py
qsharp/__init__.py
qsharp/_native.pyd
qsharp_preview-0.0.12.dist-info/RECORD
